CHANGES.txt
MANIFEST.in
README.md
setup.py
rautils/__init__.py
rautils/convert.py
rautils/manip.py
rautils/reader.py
rautils.egg-info/PKG-INFO
rautils.egg-info/SOURCES.txt
rautils.egg-info/dependency_links.txt
rautils.egg-info/top_level.txt