Metadata-Version: 2.1
Name: rautils
Version: 1.0.10
Summary: Python utility for file manipulation
Home-page: https://github.com/parthspatel/rautils
Author: Parth S. Patel
Author-email: parthspatel.nj@gmail.com
License: UNKNOWN
Platform: UNKNOWN
Classifier: Programming Language :: Python :: 3
Classifier: License :: OSI Approved :: MIT License
Classifier: Operating System :: OS Independent
